george_lucas/__init__.py
george_lucas/projector.py
george_lucas/data/a_new_hope.json
george_lucas-0.2.1.dist-info/LICENSE
george_lucas-0.2.1.dist-info/METADATA
george_lucas-0.2.1.dist-info/WHEEL
george_lucas-0.2.1.dist-info/top_level.txt
george_lucas-0.2.1.dist-info/RECORD
