Metadata-Version: 2.1
Name: george-lucas
Version: 0.2.1
Summary: Plays "A New Hope" on import
Home-page: https://github.com/deniederhut/george_lucas
Author: Dillon Niederhut
Author-email: dillon.niederhut@gmail.com
License: MIT
Platform: UNKNOWN
